detectda/__init__.py
detectda/_version.py
detectda/hlpr.py
detectda/hypo.py
detectda/idpo.py
detectda/imgs.py
detectda/tests/__init__.py
detectda/tests/test_hlpr.py
detectda/tests/test_imgs.py
detectda/tests/test_imgs_plus.npy
detectda/tests/test_plus.py
detectda/tests/test_video.pkl
detectda/tests/test_video.tif
detectda/tests/test_video_vacuum.pkl
detectda-0.5.4.dist-info/licenses/LICENSE
detectda-0.5.4.dist-info/METADATA
detectda-0.5.4.dist-info/WHEEL
detectda-0.5.4.dist-info/entry_points.txt
detectda-0.5.4.dist-info/top_level.txt
detectda-0.5.4.dist-info/RECORD
