Metadata-Version: 2.4
Name: detectda
Version: 0.5.4
Summary: detectda - detecting features in videos using TDA
Home-page: https://detectda.readthedocs.io/en/latest/
Author: Andrew M. Thomas
Author-email: <me@andrewmthomas.com>
Keywords: tda,cubical,image processing
Classifier: Operating System :: MacOS
Classifier: Operating System :: Microsoft :: Windows
Classifier: Programming Language :: Python
License-File: LICENSE
Requires-Dist: gudhi>=3.8.0
Requires-Dist: shapely>=2.0.1
Requires-Dist: joblib>=1.3.2
Requires-Dist: scikit-image>=0.21.0
Requires-Dist: scikit-learn>=0.23.1
Requires-Dist: numpy>=1.24
Requires-Dist: tqdm>=4.64.0
Requires-Dist: pandas>=1.3.0
Requires-Dist: matplotlib>=3.7.2
Requires-Dist: opencv-python>=4.10.0
Requires-Dist: scipy>=1.10.1
Requires-Dist: imagecodecs>=2021.8.26
Dynamic: author
Dynamic: author-email
Dynamic: classifier
Dynamic: description
Dynamic: description-content-type
Dynamic: home-page
Dynamic: keywords
Dynamic: license-file
Dynamic: requires-dist
Dynamic: summary
